{"type": "scene", "properties": {"baseExtent": {"cx": 4410432.62435744, "cy": 6872526.999593967, "width": 5972.2324543222785, "height": 5972.2324543222785, "rotation": 0}, "origin": {"x": 4410432.62435744, "y": 6872526.999593967, "z": 0.0}, "zScale": 1.0, "light": "directional"}, "layers": [{"type": "layer", "id": 0, "properties": {"name": "buildings-3d", "clickable": true, "visible": true, "type": "polygon", "objType": "Extruded"}, "data": {"materials": [{"type": 0, "c": 2134157}, {"type": 0, "c": 4456788}, {"type": 0, "c": 3822219}, {"type": 0, "c": 16639781}], "blocks": [{"url": "./data/index/a0.json", "featureCount": 50}, {"url": "./data/index/a1.json", "featureCount": 50}, {"url": "./data/index/a2.json", "featureCount": 42}]}}]}